nse_live_stocks/__init__.py
nse_live_stocks/main.py
nse_live_stocks-1.1.dist-info/METADATA
nse_live_stocks-1.1.dist-info/WHEEL
nse_live_stocks-1.1.dist-info/top_level.txt
nse_live_stocks-1.1.dist-info/RECORD
