Metadata-Version: 2.1
Name: nse-live-stocks
Version: 1.1
Summary: UNKNOWN
Home-page: UNKNOWN
Author: Akhil Kodati
Author-email: akhilkodati@yahoo.com
License: UNKNOWN
Platform: UNKNOWN
Requires-Python: >=3.8
Requires-Dist: requests (>=2.23.0)
